{"Sound": {"trans": "протока Зунд", "audio": {"gb": ["w/gb/gb_sound.mp3"]}, "gb": "|saʊnd|"}, "How": {"trans": "як, скільки", "audio": {"gb": ["w/gb/gb_how.mp3"]}, "gb": "|haʊ|"}, "to": {"trans": "до, щоб, на, аби", "audio": {"gb": ["w/gb/gb_to.mp3"]}, "gb": "|tuː|"}, "Pronounce": {"trans": "вимовити, вимовляти, проголошувати", "audio": {"gb": ["w/gb/gb_pronounce.mp3"]}, "gb": "|prəˈnaʊns|"}, "the": {"trans": "the", "audio": {"gb": ["w/gb/gb_the.mp3"]}, "gb": "|ði:|"}, "sound": {"trans": "звук, звучати, здоровий", "audio": {"gb": ["w/gb/gb_sound.mp3"]}, "gb": "|saʊnd|"}, "Phoneme": {"trans": "фонема, Фонема", "audio": {"gb": ["w/gb/gb_phoneme.mp3"]}, "gb": "|ˈfəʊniːm|"}, "This": {"trans": "цей, це, ця, ці, This", "audio": {"gb": ["w/gb/gb_this.mp3"]}, "gb": "|ðɪs|"}, "As": {"trans": "як, коли, оскільки", "audio": {"gb": ["w/gb/gb_as.mp3"]}, "gb": "|æz|"}, "in": {"trans": "в, у, ув, уві, у травні", "audio": {"gb": ["w/gb/gb_in.mp3"]}, "gb": "|ɪn|"}, "words": {"trans": "", "audio": {"gb": ["w/gb/gb_words.mp3"]}, "gb": "|ˈwɜːdz|", "wforms": " present tense(he/she/it) для дієслова to word, множина для іменника word", "awords": ["word"]}, "word": {"trans": "слово, називати, назвати, транскрипція, машинне слово", "audio": {"gb": ["w/gb/gb_word.mp3"]}, "gb": "|wɜːd|"}, "after": {"trans": "після, за, через", "audio": {"gb": ["w/gb/gb_after.mp3"]}, "gb": "|ˈɑːftə|"}, "last": {"trans": "останній, минулий, тривати, попередній, Лашт", "audio": {"gb": ["w/gb/gb_last.mp3"]}, "gb": "|lɑːst|"}, "ask": {"trans": "просити, питати, попросити", "audio": {"gb": ["w/gb/gb_ask.mp3"]}, "gb": "|ɑːsk|"}, "Vowel": {"trans": "голосний, голосний звук, Голосний звук", "audio": {"gb": ["w/gb/gb_vowel.mp3"]}, "gb": "|ˈvaʊəl|"}, "and": {"trans": "і, й, та", "audio": {"gb": ["w/gb/gb_and.mp3"]}, "gb": "|ænd|"}, "technical": {"trans": "технічний, транскрипція", "audio": {"gb": ["w/gb/gb_technical.mp3"]}, "gb": "|ˈteknɪk(ə)l|"}, "name": {"trans": "ім'я, назва, репутація", "audio": {"gb": ["w/gb/gb_name.mp3"]}, "gb": "|neɪm|"}, "Open": {"trans": "відкривати, відкрити, відкритий", "audio": {"gb": ["w/gb/gb_open.mp3"]}, "gb": "|ˈəʊpən|"}, "Back": {"trans": "Назад", "audio": {"gb": ["w/gb/gb_back.mp3"]}, "gb": "|bæk|"}, "Remember": {"trans": "пам'ятати", "audio": {"gb": ["w/gb/gb_remember.mp3"]}, "gb": "|rɪˈmembə|"}, "that": {"trans": "що, той, те", "audio": {"gb": ["w/gb/gb_that.mp3"]}, "gb": "|ðæt|"}, "key": {"trans": "ключ, клавіша, Ключ", "audio": {"gb": ["w/gb/gb_key.mp3"]}, "gb": "|kiː|"}, "pronunciation": {"trans": "вимова, вимовляння, транскрипція", "audio": {"gb": ["w/gb/gb_pronunciation.mp3"]}, "gb": "|prəˌnʌnsɪˈeɪʃ(ə)n|"}, "physical": {"trans": "фізичний, транскрипція, фізична", "audio": {"gb": ["w/gb/gb_physical.mp3"]}, "gb": "|ˈfɪzɪk(ə)l|"}, "tells": {"audio": {"gb": ["w/gb/gb_tells.mp3"]}, "gb": "|telz|", "wforms": " present tense(he/she/it) для дієслова to tell", "awords": ["tell"], "trans": ""}, "tell": {"trans": "казати, наказувати, запевняти, Тель", "audio": {"gb": ["w/gb/gb_tell.mp3"]}, "gb": "|tel|", "wforms": " irregular verb:  p.t. —  told  p.p. —  told "}, "us": {"trans": "нас, нам, нами", "audio": {"gb": ["w/gb/gb_us.mp3"]}, "gb": "|ʌs|"}, "about": {"trans": "про, приблизно, близько", "audio": {"gb": ["w/gb/gb_about.mp3"]}, "gb": "|əˈbaʊt|"}, "how": {"trans": "як, скільки", "audio": {"gb": ["w/gb/gb_how.mp3"]}, "gb": "|haʊ|"}, "made": {"trans": "", "audio": {"gb": ["w/gb/gb_made.mp3"]}, "gb": "|ˈmeɪd|", "wforms": " 2-а,3-я форма дієслова to make", "awords": ["make"]}, "make": {"trans": "робити, зробити, виготовляти", "audio": {"gb": ["w/gb/gb_make.mp3"]}, "gb": "|meɪk|", "wforms": " irregular verb:  p.t. —  made  p.p. —  made "}, "physically": {"trans": "", "audio": {"gb": ["w/gb/gb_physically.mp3"]}, "gb": "|ˈfɪzɪkəli|"}, "In": {"trans": "в, у, ув, уві, у травні", "audio": {"gb": ["w/gb/gb_in.mp3"]}, "gb": "|ɪn|"}, "this": {"trans": "цей, це, ця, ці, This", "audio": {"gb": ["w/gb/gb_this.mp3"]}, "gb": "|ðɪs|"}, "case": {"trans": "відмінок, скриня, випадок", "audio": {"gb": ["w/gb/gb_case.mp3"]}, "gb": "|keɪs|"}, "your": {"trans": "ваш, твій", "audio": {"gb": ["w/gb/gb_your.mp3"]}, "gb": "|jə|"}, "tongue": {"trans": "язик, мова", "audio": {"gb": ["w/gb/gb_tongue.mp3"]}, "gb": "|tʌŋ|"}, "low": {"trans": "низький, низько, внизу", "audio": {"gb": ["w/gb/gb_low.mp3"]}, "gb": "|ləʊ|"}, "at": {"trans": "біля, в, у", "audio": {"gb": ["w/gb/gb_at.mp3"]}, "gb": "|æt|"}, "back": {"trans": "спина, назад, зад", "audio": {"gb": ["w/gb/gb_back.mp3"]}, "gb": "|bæk|"}, "of": {"trans": "про", "audio": {"gb": ["w/gb/gb_of.mp3"]}, "gb": "|ɒv|"}, "mouth": {"trans": "рот, вуста, паща", "audio": {"gb": ["w/gb/gb_mouth.mp3"]}, "gb": "|maʊθ|"}, "refers": {"audio": {"gb": ["w/gb/gb_refers.mp3"]}, "gb": "|rɪˈfɜːz|", "wforms": " present tense(he/she/it) для дієслова to refer", "awords": ["refer"], "trans": ""}, "refer": {"trans": "згадувати", "audio": {"gb": ["w/gb/gb_refer.mp3"]}, "gb": "|rɪˈfɜː|"}, "lips": {"gb": "|lɪps|", "wforms": " множина для іменника lip", "awords": ["lip"], "trans": ""}, "lip": {"trans": "губа, Губи, губи", "audio": {"gb": ["w/gb/gb_lip.mp3"]}, "gb": "|lɪp|"}, "because": {"trans": "бо, тому що, адже", "audio": {"gb": ["w/gb/gb_because.mp3"]}, "gb": "|bɪˈkəz|"}, "they": {"trans": "вони", "audio": {"gb": ["w/gb/gb_they.mp3"]}, "gb": "|ðeɪ|"}, "are": {"trans": "ар, га особа sing і pres. від to be, Ар, є", "audio": {"gb": ["w/gb/gb_are.mp3"]}, "gb": "|ɑː|"}, "relaxed": {"trans": "", "audio": {"gb": ["w/gb/gb_relaxed.mp3"]}, "gb": "|rɪˈlækst|", "wforms": " 2-а,3-я форма дієслова to relax", "awords": ["relax"]}, "relax": {"trans": "відпочивати", "audio": {"gb": ["w/gb/gb_relax.mp3"]}, "gb": "|rɪˈlæks|"}, "rounded": {"trans": "", "audio": {"gb": ["w/gb/gb_rounded.mp3"]}, "gb": "|ˈraʊndɪd|", "wforms": " 2-а,3-я форма дієслова to round", "awords": ["round"]}, "round": {"trans": "круглий, коло, круг, навколо, раунд", "audio": {"gb": ["w/gb/gb_round.mp3"]}, "gb": "|raʊnd|"}, "All": {"trans": "все, всі, кожен", "audio": {"gb": ["w/gb/gb_all.mp3"]}, "gb": "|ɔːl|"}, "vowels": {"audio": {"gb": ["w/gb/gb_vowels.mp3"]}, "gb": "|ˈvaʊəlz|", "wforms": " множина для іменника vowel", "awords": ["vowel"], "trans": ""}, "vowel": {"trans": "голосний, голосний звук, Голосний звук", "audio": {"gb": ["w/gb/gb_vowel.mp3"]}, "gb": "|ˈvaʊəl|"}, "through": {"trans": "через, крізь", "audio": {"gb": ["w/gb/gb_through.mp3"]}, "gb": "|θruː|"}, "voiced": {"trans": "", "audio": {"gb": ["w/gb/gb_voiced.mp3"]}, "gb": "|vɔɪst|", "wforms": " 2-а,3-я форма дієслова to voice", "awords": ["voice"]}, "voice": {"trans": "голос, Дзвінкість, застава, стан", "audio": {"gb": ["w/gb/gb_voice.mp3"]}, "gb": "|vɔɪs|"}, "so": {"trans": "так, такий, тож", "audio": {"gb": ["w/gb/gb_so.mp3"]}, "gb": "|səʊ|"}, "you": {"trans": "ви, ти, вас, викати", "audio": {"gb": ["w/gb/gb_you.mp3"]}, "gb": "|ju|"}, "vibrate": {"trans": "", "audio": {"gb": ["w/gb/gb_vibrate.mp3"]}, "gb": "|vaɪˈbreɪt|"}, "vocal": {"trans": "", "audio": {"gb": ["w/gb/gb_vocal.mp3"]}, "gb": "|ˈvəʊk(ə)l|"}, "chords": {"audio": {"gb": ["w/gb/gb_chords.mp3"]}, "gb": "|kɔːdz|", "wforms": " множина для іменника chord", "awords": ["chord"], "trans": ""}, "chord": {"trans": "акорд, хорда, Акорд, Хорда, акордний", "audio": {"gb": ["w/gb/gb_chord.mp3"]}, "gb": "|kɔːd|"}, "similar": {"trans": "схожий, подібний", "audio": {"gb": ["w/gb/gb_similar.mp3"]}, "gb": "|ˈsɪmɪlə|"}, "but": {"trans": "але, а, крім, однак, окрім", "audio": {"gb": ["w/gb/gb_but.mp3"]}, "gb": "|bʌt|"}, "two": {"trans": "два, двійка, дві", "audio": {"gb": ["w/gb/gb_two.mp3"]}, "gb": "|tuː|"}, "little": {"trans": "маленький, малий, мало", "audio": {"gb": ["w/gb/gb_little.mp3"]}, "gb": "|ˈlɪt(ə)l|"}, "dots": {"audio": {"gb": ["w/gb/gb_dots.mp3"]}, "gb": "|dɒts|", "wforms": " present tense(he/she/it) для дієслова to dot, множина для іменника dot", "awords": ["dot"], "trans": ""}, "dot": {"trans": "крапка, точка, дот", "audio": {"gb": ["w/gb/gb_dot.mp3"]}, "gb": "|dɒt|"}, "mean": {"trans": "означати, значити, мати на увазі", "audio": {"gb": ["w/gb/gb_mean.mp3"]}, "gb": "|miːn|", "wforms": " irregular verb:  p.t. —  meant  p.p. —  meant "}, "longer": {"trans": "довше", "audio": {"gb": ["w/gb/gb_longer.mp3"]}, "gb": "|ˈlɒŋɡə|", "wforms": " вищий ступінь порівняння (comparative) для прикметника long", "awords": ["long"]}, "long": {"trans": "довгий, довго, тривалий", "audio": {"gb": ["w/gb/gb_long.mp3"]}, "gb": "|lɒŋ|"}, "sounds": {"trans": "", "audio": {"gb": ["w/gb/gb_sounds.mp3"]}, "gb": "|ˈsaʊndz|", "wforms": " present tense(he/she/it) для дієслова to sound, множина для іменника sound", "awords": ["sound"]}, "To": {"trans": "до, щоб, на, аби", "audio": {"gb": ["w/gb/gb_to.mp3"]}, "gb": "|tuː|"}, "produce": {"trans": "виробляти, видати, виріб", "audio": {"gb": ["w/gb/gb_produce.mp3"]}, "gb": "|prəˈdjuːs|"}, "put": {"trans": "класти, ставити, посадити", "audio": {"gb": ["w/gb/gb_put.mp3"]}, "gb": "|pʊt|", "wforms": " irregular verb:  p.t. —  put  p.p. —  put "}, "then": {"trans": "тоді, потім", "audio": {"gb": ["w/gb/gb_then.mp3"]}, "gb": "|ðen|"}, "with": {"trans": "з, зі, із", "audio": {"gb": ["w/gb/gb_with.mp3"]}, "gb": "|wɪð|"}, "open": {"trans": "відкривати, відкрити, відкритий", "audio": {"gb": ["w/gb/gb_open.mp3"]}, "gb": "|ˈəʊpən|"}, "The": {"trans": "транскрипція", "audio": {"gb": ["w/gb/gb_the.mp3"]}, "gb": "|ði:|"}, "letters": {"trans": "листування", "audio": {"gb": ["w/gb/gb_letters.mp3"]}, "gb": "|ˈletəz|", "wforms": " множина для іменника letter", "awords": ["letter"]}, "letter": {"trans": "буква, лист, літера, послання", "audio": {"gb": ["w/gb/gb_letter.mp3"]}, "gb": "|ˈletə|"}, "as": {"trans": "як, коли, оскільки", "audio": {"gb": ["w/gb/gb_as.mp3"]}, "gb": "|æz|"}, "start": {"trans": "починати, початок, починатися", "audio": {"gb": ["w/gb/gb_start.mp3"]}, "gb": "|stɑːt|"}, "part": {"trans": "частина, частка, порція", "audio": {"gb": ["w/gb/gb_part.mp3"]}, "gb": "|pɑːt|"}, "large": {"trans": "великий, величезний", "audio": {"gb": ["w/gb/gb_large.mp3"]}, "gb": "|lɑːdʒ|"}, "party": {"trans": "партія, вечірка, сторона", "audio": {"gb": ["w/gb/gb_party.mp3"]}, "gb": "|ˈpɑːti|"}, "Like": {"trans": "як, подобатися, любити", "audio": {"gb": ["w/gb/gb_like.mp3"]}, "gb": "|laɪk|"}, "all": {"trans": "все, всі, кожен", "audio": {"gb": ["w/gb/gb_all.mp3"]}, "gb": "|ɔːl|"}, "English": {"trans": "англійська, англійський, англієць", "audio": {"gb": ["w/gb/gb_english.mp3"]}, "gb": "|ˈɪŋɡlɪʃ|"}, "spelling": {"trans": "правопис, орфографія", "audio": {"gb": ["w/gb/gb_spelling.mp3"]}, "gb": "|ˈspelɪŋ|", "wforms": " ing-форма дієслова to spell", "awords": ["spell"]}, "spell": {"trans": "закляття, заклинання, чари, писати", "audio": {"gb": ["w/gb/gb_spell.mp3"]}, "gb": "|spel|", "wforms": " irregular verb:  p.t. —  spelt or spelled  p.p. —  spelt or spelled "}, "can": {"trans": "могти, вміти, уміти", "audio": {"gb": ["w/gb/gb_can.mp3"]}, "gb": "|kæn|"}, "be": {"trans": "бути, знаходитися, існувати, з'являтися, являтися", "audio": {"gb": ["w/gb/gb_be.mp3"]}, "gb": "|bi|", "wforms": " irregular verb:  p.t. —  were/was  p.p. —  been "}, "very": {"trans": "дуже, вельми, значно, надто", "audio": {"gb": ["w/gb/gb_very.mp3"]}, "gb": "|ˈveri|"}, "inconsistent": {"trans": "непослідовний", "audio": {"gb": ["w/gb/gb_inconsistent.mp3"]}, "gb": "|ɪnkənˈsɪst(ə)nt|"}, "will": {"trans": "воля, заповіт, Заповіт, тестамент", "audio": {"gb": ["w/gb/gb_will.mp3"]}, "gb": "|wɪl|"}, "always": {"trans": "завжди, завше, постійно", "audio": {"gb": ["w/gb/gb_always.mp3"]}, "gb": "|ˈɔːlweɪz|"}, "find": {"trans": "знайти, знаходити, виявити", "audio": {"gb": ["w/gb/gb_find.mp3"]}, "gb": "|faɪnd|", "wforms": " irregular verb:  p.t. —  found  p.p. —  found "}, "alternative": {"trans": "альтернативний, альтернатива, вибір", "audio": {"gb": ["w/gb/gb_alternative.mp3"]}, "gb": "|ɔːlˈtɜːnətɪv|"}, "unusual": {"trans": "незвичайний, незвичний", "audio": {"gb": ["w/gb/gb_unusual.mp3"]}, "gb": "|ʌnˈjuːʒʊəl|"}, "spellings": {"audio": {"gb": ["w/gb/gb_spellings.mp3"]}, "gb": "|ˈspelɪŋz|", "wforms": " множина для іменника spelling", "awords": ["spelling"], "trans": ""}, "one": {"trans": "один, одиниця, одна", "audio": {"gb": ["w/gb/gb_one.mp3"]}, "gb": "|wʌn|"}, "most": {"trans": "більш, більшість, найбільш, найбільше", "audio": {"gb": ["w/gb/gb_most.mp3"]}, "gb": "|məʊst|"}, "difficult": {"trans": "важкий, трудний", "audio": {"gb": ["w/gb/gb_difficult.mp3"]}, "gb": "|ˈdɪfɪk(ə)lt|"}, "things": {"trans": "", "audio": {"gb": ["w/gb/gb_things.mp3"]}, "gb": "|ˈθɪŋz|", "wforms": " множина для іменника thing", "awords": ["thing"]}, "thing": {"trans": "річ, предмет, Тінґ", "audio": {"gb": ["w/gb/gb_thing.mp3"]}, "gb": "|θɪŋ|"}, "just": {"trans": "просто, тільки, щойно, справедливий", "audio": {"gb": ["w/gb/gb_just.mp3"]}, "gb": "|dʒəst|"}, "have": {"trans": "мати, у, в, повинен", "audio": {"gb": ["w/gb/gb_have.mp3"]}, "gb": "|hæv|", "wforms": " irregular verb:  p.t. —  had  p.p. —  had "}, "learn": {"trans": "учитися, дізнатися, вчитися", "audio": {"gb": ["w/gb/gb_learn.mp3"]}, "gb": "|lɜːn|", "wforms": " irregular verb:  p.t. —  learnt or learned  p.p. —  learnt or learned "}, "Examples": {"audio": {"gb": ["w/gb/gb_examples.mp3"]}, "gb": "|ɪɡˈzɑːmpəlz|", "wforms": " множина для іменника example", "awords": ["example"], "trans": ""}, "example": {"trans": "приклад", "audio": {"gb": ["w/gb/gb_example.mp3"]}, "gb": "|ɪɡˈzɑːmp(ə)l|"}, "Here": {"trans": "тут, сюди, ось", "audio": {"gb": ["w/gb/gb_here.mp3"]}, "gb": "|hɪə|"}, "some": {"trans": "трохи, кілька, деякий", "audio": {"gb": ["w/gb/gb_some.mp3"]}, "gb": "|sʌm|"}, "art": {"trans": "мистецтво, уміння, майстерність", "audio": {"gb": ["w/gb/gb_art.mp3"]}, "gb": "|ɑːt|"}, "arm": {"trans": "рука, зброя, рукав", "audio": {"gb": ["w/gb/gb_arm.mp3"]}, "gb": "|ɑːm|"}, "answer": {"trans": "відповідати, відповідь, відповісти", "audio": {"gb": ["w/gb/gb_answer.mp3"]}, "gb": "|ˈɑːnsə|"}, "argue": {"trans": "сперечатися, доводити, твердити", "audio": {"gb": ["w/gb/gb_argue.mp3"]}, "gb": "|ˈɑːɡjuː|"}, "middle": {"trans": "середній, середина", "audio": {"gb": ["w/gb/gb_middle.mp3"]}, "gb": "|ˈmɪd(ə)l|"}, "father": {"trans": "батько, тато, отець, татусь, татко", "audio": {"gb": ["w/gb/gb_father.mp3"]}, "gb": "|ˈfɑːðə|"}, "market": {"trans": "ринок, базар, Ринок", "audio": {"gb": ["w/gb/gb_market.mp3"]}, "gb": "|ˈmɑːkɪt|"}, "class": {"trans": "клас", "audio": {"gb": ["w/gb/gb_class.mp3"]}, "gb": "|klɑːs|"}, "hard": {"trans": "твердий, важко, жорсткий", "audio": {"gb": ["w/gb/gb_hard.mp3"]}, "gb": "|hɑːd|"}, "end": {"trans": "кінець, край, закінчити", "audio": {"gb": ["w/gb/gb_end.mp3"]}, "gb": "|end|"}, "far": {"trans": "далеко, далекий, дальній", "audio": {"gb": ["w/gb/gb_far.mp3"]}, "gb": "|fɑː|"}, "car": {"trans": "автомобіль, авто, машина", "audio": {"gb": ["w/gb/gb_car.mp3"]}, "gb": "|kɑː|"}, "star": {"trans": "зірка, зоря, звізда, зiрка", "audio": {"gb": ["w/gb/gb_star.mp3"]}, "gb": "|stɑː|"}, "bar": {"trans": "бар, такт, кабак", "audio": {"gb": ["w/gb/gb_bar.mp3"]}, "gb": "|bɑː|"}, "So": {"trans": "так, такий, тож", "audio": {"gb": ["w/gb/gb_so.mp3"]}, "gb": "|səʊ|"}, "for": {"trans": "для, бо, від", "audio": {"gb": ["w/gb/gb_for.mp3"]}, "gb": "|fɔː|"}, "we": {"trans": "ми", "audio": {"gb": ["w/gb/gb_we.mp3"]}, "gb": "|wi|"}, "additional": {"trans": "додатковий", "audio": {"gb": ["w/gb/gb_additional.mp3"]}, "gb": "|əˈdɪʃ(ə)n(ə)l|"}, "videos": {"audio": {"gb": ["w/gb/gb_videos.mp3"]}, "gb": "|ˈvɪdɪəʊz|", "wforms": " present tense(he/she/it) для дієслова to video, множина для іменника video", "awords": ["video"], "trans": ""}, "video": {"trans": "відео", "audio": {"gb": ["w/gb/gb_video.mp3"]}, "gb": "|ˈvɪdɪəʊ|"}, "on": {"trans": "на, по", "audio": {"gb": ["w/gb/gb_on.mp3"]}, "gb": "|ɒn|"}, "each": {"trans": "кожний, кожен, кожнийкожен)", "audio": {"gb": ["w/gb/gb_each.mp3"]}, "gb": "|iːtʃ|"}, "groups": {"trans": "", "audio": {"gb": ["w/gb/gb_groups.mp3"]}, "gb": "|ɡruːps|", "wforms": " present tense(he/she/it) для дієслова to group, множина для іменника group", "awords": ["group"]}, "group": {"trans": "група, ансамбль, угруповання", "audio": {"gb": ["w/gb/gb_group.mp3"]}, "gb": "|ɡruːp|"}, "Vowels": {"audio": {"gb": ["w/gb/gb_vowels.mp3"]}, "gb": "|ˈvaʊəlz|", "wforms": " множина для іменника vowel", "awords": ["vowel"], "trans": ""}, "Diphthongs": {"gb": "|ˈdɪfθɒŋz|", "wforms": " множина для іменника diphthong", "awords": ["diphthong"], "trans": ""}, "diphthong": {"trans": "дифтонг, двоголосівка", "audio": {"gb": ["w/gb/gb_diphthong.mp3"]}, "gb": "|ˈdɪfθɒŋ|"}, "Single": {"trans": "сингл, вільний, один", "audio": {"gb": ["w/gb/gb_single.mp3"]}, "gb": "|ˈsɪŋɡ(ə)l|"}, "Consonants": {"audio": {"gb": ["w/gb/gb_consonants.mp3"]}, "gb": "|ˈkɒnsənənts|", "wforms": " множина для іменника consonant", "awords": ["consonant"], "trans": ""}, "consonant": {"trans": "приголосний, приголосна, шелестівка, приголосний звук, Приголосний звук", "audio": {"gb": ["w/gb/gb_consonant.mp3"]}, "gb": "|ˈkɒns(ə)nənt|"}, "or": {"trans": "або, чи, Золото", "audio": {"gb": ["w/gb/gb_or.mp3"]}, "gb": "|ɔː|"}, "Consonant": {"trans": "приголосний, приголосна, шелестівка, приголосний звук, Приголосний звук", "audio": {"gb": ["w/gb/gb_consonant.mp3"]}, "gb": "|ˈkɒns(ə)nənt|"}, "Pairs": {"trans": "", "audio": {"gb": ["w/gb/gb_pairs.mp3"]}, "gb": "|peəz|", "wforms": " present tense(he/she/it) для дієслова to pair, множина для іменника pair", "awords": ["pair"]}, "pair": {"trans": "пара, створити пару", "audio": {"gb": ["w/gb/gb_pair.mp3"]}, "gb": "|peə|"}, "well": {"trans": "добре, колодязь, гарно", "audio": {"gb": ["w/gb/gb_well.mp3"]}, "gb": "|wel|"}, "explaining": {"audio": {"gb": ["w/gb/gb_explaining.mp3"]}, "gb": "|ɪkˈspleɪnɪŋ|", "wforms": " ing-форма дієслова to explain", "awords": ["explain"], "trans": ""}, "explain": {"trans": "пояснити, пояснювати", "audio": {"gb": ["w/gb/gb_explain.mp3"]}, "gb": "|ɪkˈspleɪn|"}, "phonetic": {"trans": "фонетичний", "audio": {"gb": ["w/gb/gb_phonetic.mp3"]}, "gb": "|fəˈnetɪk|"}, "chart": {"trans": "діаграма, схема, карта, мапа", "audio": {"gb": ["w/gb/gb_chart.mp3"]}, "gb": "|tʃɑːt|"}}