{"In": {"trans": "в, у, ув, уві, у травні", "audio": {"gb": ["w/gb/gb_in.mp3"]}, "gb": "|ɪn|"}, "the": {"trans": "the", "audio": {"gb": ["w/gb/gb_the.mp3"]}, "gb": "|ði:|"}, "year": {"trans": "рік, курс, клас", "audio": {"gb": ["w/gb/gb_year.mp3"]}, "gb": "|jɪə|"}, "took": {"trans": "", "audio": {"gb": ["w/gb/gb_took.mp3"]}, "gb": "|tʊk|", "wforms": " 2-а форма неправильного дієслова to take", "awords": ["take"]}, "take": {"trans": "брати, взяти, узяти", "audio": {"gb": ["w/gb/gb_take.mp3"]}, "gb": "|teɪk|", "wforms": " irregular verb:  p.t. —  took  p.p. —  taken "}, "my": {"trans": "мій", "audio": {"gb": ["w/gb/gb_my.mp3"]}, "gb": "|maɪ|"}, "degree": {"trans": "градус, ступінь", "audio": {"gb": ["w/gb/gb_degree.mp3"]}, "gb": "|dɪˈɡriː|"}, "of": {"trans": "про", "audio": {"gb": ["w/gb/gb_of.mp3"]}, "gb": "|ɒv|"}, "Doctor": {"trans": "лікар, доктор", "audio": {"gb": ["w/gb/gb_doctor.mp3"]}, "gb": "|ˈdɒktə|"}, "Medicine": {"trans": "медицина, лік, ліки", "audio": {"gb": ["w/gb/gb_medicine.mp3"]}, "gb": "|ˈmeds(ə)n|"}, "University": {"trans": "університет, вищий навчальний заклад, університетський", "audio": {"gb": ["w/gb/gb_university.mp3"]}, "gb": "|juːnɪˈvɜːsɪti|"}, "London": {"trans": "Лондон", "audio": {"gb": ["w/gb/gb_london.mp3"]}, "gb": "|ˈlʌndən|"}, "and": {"trans": "і, й, та", "audio": {"gb": ["w/gb/gb_and.mp3"]}, "gb": "|ænd|"}, "proceeded": {"audio": {"gb": ["w/gb/gb_proceeded.mp3"]}, "gb": "|prəˈsiːdɪd|", "wforms": " 2-а,3-я форма дієслова to proceed", "awords": ["proceed"], "trans": ""}, "proceed": {"trans": "продовжити", "audio": {"gb": ["w/gb/gb_proceed.mp3"]}, "gb": "|prəˈsiːd|"}, "to": {"trans": "до, щоб, на, аби", "audio": {"gb": ["w/gb/gb_to.mp3"]}, "gb": "|tuː|"}, "go": {"trans": "іти, ходити, йти", "audio": {"gb": ["w/gb/gb_go.mp3"]}, "gb": "|ɡəʊ|", "wforms": " irregular verb:  p.t. —  went  p.p. —  gone "}, "through": {"trans": "через, крізь", "audio": {"gb": ["w/gb/gb_through.mp3"]}, "gb": "|θruː|"}, "course": {"trans": "курс, хід, біг", "audio": {"gb": ["w/gb/gb_course.mp3"]}, "gb": "|kɔːs|"}, "prescribed": {"trans": "", "audio": {"gb": ["w/gb/gb_prescribed.mp3"]}, "gb": "|prɪˈskraɪbd|", "wforms": " 2-а,3-я форма дієслова to prescribe", "awords": ["prescribe"]}, "prescribe": {"trans": "призначати", "audio": {"gb": ["w/gb/gb_prescribe.mp3"]}, "gb": "|prɪˈskraɪb|"}, "for": {"trans": "для, бо, від", "audio": {"gb": ["w/gb/gb_for.mp3"]}, "gb": "|fɔː|"}, "surgeons": {"audio": {"gb": ["w/gb/gb_surgeons.mp3"]}, "gb": "|ˈsɜːdʒənz|", "wforms": " множина для іменника surgeon", "awords": ["surgeon"], "trans": ""}, "surgeon": {"trans": "хірург", "audio": {"gb": ["w/gb/gb_surgeon.mp3"]}, "gb": "|ˈsɜːdʒ(ə)n|"}, "in": {"trans": "в, у, ув, уві, у травні", "audio": {"gb": ["w/gb/gb_in.mp3"]}, "gb": "|ɪn|"}, "Army": {"trans": "Армія", "audio": {"gb": ["w/gb/gb_army.mp3"]}, "gb": "|ˈɑːmi|"}, "Having": {"trans": "", "audio": {"gb": ["w/gb/gb_having.mp3"]}, "gb": "|ˈhævɪŋ|", "wforms": " ing-форма дієслова to have", "awords": ["have"]}, "have": {"trans": "мати, у, в, повинен", "audio": {"gb": ["w/gb/gb_have.mp3"]}, "gb": "|hæv|", "wforms": " irregular verb:  p.t. —  had  p.p. —  had "}, "completed": {"trans": "завершено", "audio": {"gb": ["w/gb/gb_completed.mp3"]}, "gb": "|kəmˈpliːtɪd|", "wforms": " 2-а,3-я форма дієслова to complete", "awords": ["complete"]}, "complete": {"trans": "повний, завершувати, закінчувати", "audio": {"gb": ["w/gb/gb_complete.mp3"]}, "gb": "|kəmˈpliːt|"}, "studies": {"trans": "навчання", "audio": {"gb": ["w/gb/gb_studies.mp3"]}, "gb": "|ˈstʌdɪz|", "wforms": " present tense(he/she/it) для дієслова to study, множина для іменника study", "awords": ["study"]}, "study": {"trans": "вчитися, учитися, навчатися", "audio": {"gb": ["w/gb/gb_study.mp3"]}, "gb": "|ˈstʌdi|"}, "there": {"trans": "там, туди, ось, от", "audio": {"gb": ["w/gb/gb_there.mp3"]}, "gb": "|ðeə|"}, "was": {"trans": "читач", "audio": {"gb": ["w/gb/gb_was.mp3"]}, "gb": "|wɒz|"}, "duly": {"trans": "", "audio": {"gb": ["w/gb/gb_duly.mp3"]}, "gb": "|ˈdjuːli|"}, "attached": {"trans": "арештований, відданий, доданий", "audio": {"gb": ["w/gb/gb_attached.mp3"]}, "gb": "|əˈtætʃt|", "wforms": " 2-а,3-я форма дієслова to attach", "awords": ["attach"]}, "attach": {"trans": "надавати, приєднувати, прикомандировувати", "audio": {"gb": ["w/gb/gb_attach.mp3"]}, "gb": "|əˈtætʃ|"}, "Fifth": {"trans": "п'ятий, пʼятий, квінта, п’ятий", "audio": {"gb": ["w/gb/gb_fifth.mp3"]}, "gb": "|fɪfθ|"}, "Northumberland": {"trans": "Нортумберленд", "audio": {"gb": ["w/gb/gb_northumberland.mp3"]}, "gb": "|nɔːˈθʌmbələnd|"}, "Fusiliers": {"gb": "|ˌfjuːzəˈlɪəz|", "wforms": " множина для іменника fusilier", "awords": ["fusilier"], "trans": ""}, "fusilier": {"trans": "Фузілери, стрілець", "audio": {"gb": ["w/gb/gb_fusilier.mp3"]}, "gb": "|ˌfjuːzɪˈlɪə|"}, "as": {"trans": "як, коли, оскільки", "audio": {"gb": ["w/gb/gb_as.mp3"]}, "gb": "|æz|"}, "assistant": {"trans": "помічник, асистент, допоміжний засіб", "audio": {"gb": ["w/gb/gb_assistant.mp3"]}, "gb": "|əˈsɪst(ə)nt|"}, "The": {"trans": "транскрипція", "audio": {"gb": ["w/gb/gb_the.mp3"]}, "gb": "|ði:|"}, "regiment": {"trans": "полк, Полковий устрій України", "audio": {"gb": ["w/gb/gb_regiment.mp3"]}, "gb": "|ˈredʒɪmənt|"}, "stationed": {"audio": {"gb": ["w/gb/gb_stationed.mp3"]}, "gb": "|ˈsteɪʃənd|", "wforms": " 2-а,3-я форма дієслова to station", "awords": ["station"], "trans": ""}, "station": {"trans": "станція, вокзал, дислокувати", "audio": {"gb": ["w/gb/gb_station.mp3"]}, "gb": "|ˈsteɪʃ(ə)n|"}, "India": {"trans": "Індія, iндiя", "audio": {"gb": ["w/gb/gb_india.mp3"]}, "gb": "|ˈɪndɪə|"}, "at": {"trans": "біля, в, у", "audio": {"gb": ["w/gb/gb_at.mp3"]}, "gb": "|æt|"}, "time": {"trans": "час, раз, година", "audio": {"gb": ["w/gb/gb_time.mp3"]}, "gb": "|taɪm|"}, "before": {"trans": "під, перед, раніше, попереду, спереду", "audio": {"gb": ["w/gb/gb_before.mp3"]}, "gb": "|bɪˈfɔː|"}, "could": {"trans": "могти", "audio": {"gb": ["w/gb/gb_could.mp3"]}, "gb": "|kʊd|"}, "join": {"trans": "приєднуватися, вступати, об’єднання, з’єднувати, Джойн", "audio": {"gb": ["w/gb/gb_join.mp3"]}, "gb": "|dʒɔɪn|"}, "second": {"trans": "секунда, другий, мить", "audio": {"gb": ["w/gb/gb_second.mp3"]}, "gb": "|ˈsek(ə)nd|"}, "Afghan": {"trans": "афганець, афганський, афганка", "audio": {"gb": ["w/gb/gb_afghan.mp3"]}, "gb": "|ˈæfɡæn|"}, "war": {"trans": "війна", "audio": {"gb": ["w/gb/gb_war.mp3"]}, "gb": "|wɔː|"}, "had": {"trans": "", "audio": {"gb": ["w/gb/gb_had.mp3"]}, "gb": "|hæd|", "wforms": " 2-а,3-я форма дієслова to have", "awords": ["have"]}, "broken": {"trans": "зламаний", "audio": {"gb": ["w/gb/gb_broken.mp3"]}, "gb": "|ˈbrəʊk(ə)n|", "wforms": " 3-я форма неправильного дієслова to break", "awords": ["break"]}, "break": {"trans": "ламати, зламати, розбити", "audio": {"gb": ["w/gb/gb_break.mp3"]}, "gb": "|breɪk|", "wforms": " irregular verb:  p.t. —  broke  p.p. —  broken "}, "out": {"trans": "аут, з", "audio": {"gb": ["w/gb/gb_out.mp3"]}, "gb": "|aʊt|"}, "On": {"trans": "на, по", "audio": {"gb": ["w/gb/gb_on.mp3"]}, "gb": "|ɒn|"}, "landing": {"trans": "посадка, приземлення, Посадка літального об'єкту, посадка літального об'єкту", "audio": {"gb": ["w/gb/gb_landing.mp3"]}, "gb": "|ˈlændɪŋ|", "wforms": " ing-форма дієслова to land", "awords": ["land"]}, "land": {"trans": "земля, приземлятися, приземлитися", "audio": {"gb": ["w/gb/gb_land.mp3"]}, "gb": "|lænd|"}, "Bombay": {"trans": "Бомбей, Мумбай, Мумбаї", "audio": {"gb": ["w/gb/gb_bombay.mp3"]}, "gb": "|bɒmˈbeɪ|"}, "learned": {"trans": "", "audio": {"gb": ["w/gb/gb_learned.mp3"]}, "gb": "|ˈlɜːnɪd|"}, "that": {"trans": "що, той, те", "audio": {"gb": ["w/gb/gb_that.mp3"]}, "gb": "|ðæt|"}, "corps": {"trans": "Корпус, корпус, стадо", "audio": {"gb": ["w/gb/gb_corps.mp3"]}, "gb": "|kɔː|"}, "advanced": {"trans": "висунутий уперед, передовий, прогресивний", "audio": {"gb": ["w/gb/gb_advanced.mp3"]}, "gb": "|ædˈvɑːnst|", "wforms": " 2-а,3-я форма дієслова to advance", "awords": ["advance"]}, "advance": {"trans": "аванс, просування, наперед", "audio": {"gb": ["w/gb/gb_advance.mp3"]}, "gb": "|ədˈvɑːns|"}, "passes": {"audio": {"gb": ["w/gb/gb_passes.mp3"]}, "gb": "|ˈpɑːsɪz|", "wforms": " present tense(he/she/it) для дієслова to pass, множина для іменника pass", "awords": ["pass"], "trans": ""}, "pass": {"trans": "прохід, проходити, передавати, набути ім'я", "audio": {"gb": ["w/gb/gb_pass.mp3"]}, "gb": "|pɑːs|"}, "already": {"trans": "вже, уже, раніше, ще", "audio": {"gb": ["w/gb/gb_already.mp3"]}, "gb": "|ɔːlˈredi|"}, "deep": {"trans": "глибокий", "audio": {"gb": ["w/gb/gb_deep.mp3"]}, "gb": "|diːp|"}, "country": {"trans": "країна, держава, село", "audio": {"gb": ["w/gb/gb_country.mp3"]}, "gb": "|ˈkʌntri|"}, "followed": {"audio": {"gb": ["w/gb/gb_followed.mp3"]}, "gb": "|ˈfɒləʊd|", "wforms": " 2-а,3-я форма дієслова to follow", "awords": ["follow"], "trans": ""}, "follow": {"trans": "стежити, слідкувати, додержувати", "audio": {"gb": ["w/gb/gb_follow.mp3"]}, "gb": "|ˈfɒləʊ|"}, "however": {"trans": "однак, проте, але", "audio": {"gb": ["w/gb/gb_however.mp3"]}, "gb": "|haʊˈevə|"}, "with": {"trans": "з, зі, із", "audio": {"gb": ["w/gb/gb_with.mp3"]}, "gb": "|wɪð|"}, "many": {"trans": "багато, чимало", "audio": {"gb": ["w/gb/gb_many.mp3"]}, "gb": "|ˈmeni|"}, "other": {"trans": "інший, інакший", "audio": {"gb": ["w/gb/gb_other.mp3"]}, "gb": "|ˈʌðə|"}, "officers": {"audio": {"gb": ["w/gb/gb_officers.mp3"]}, "gb": "|ˈɒfɪsəz|", "wforms": " множина для іменника officer", "awords": ["officer"], "trans": ""}, "officer": {"trans": "офіцер, чиновник, офіцерський", "audio": {"gb": ["w/gb/gb_officer.mp3"]}, "gb": "|ˈɒfɪsə|"}, "who": {"trans": "хто", "audio": {"gb": ["w/gb/gb_who.mp3"]}, "gb": "|huː|"}, "were": {"trans": "", "audio": {"gb": ["w/gb/gb_were.mp3"]}, "gb": "|wɜː|"}, "same": {"trans": "одноманітний, так само", "audio": {"gb": ["w/gb/gb_same.mp3"]}, "gb": "|seɪm|"}, "situation": {"trans": "ситуація, стан, положення", "audio": {"gb": ["w/gb/gb_situation.mp3"]}, "gb": "|sɪtjʊˈeɪʃ(ə)n|"}, "myself": {"trans": "себе, ся, собою", "audio": {"gb": ["w/gb/gb_myself.mp3"]}, "gb": "|maɪˈself|"}, "succeeded": {"audio": {"gb": ["w/gb/gb_succeeded.mp3"]}, "gb": "|səkˈsiːdɪd|", "wforms": " 2-а,3-я форма дієслова to succeed", "awords": ["succeed"], "trans": ""}, "succeed": {"trans": "досягти успіху", "audio": {"gb": ["w/gb/gb_succeed.mp3"]}, "gb": "|səkˈsiːd|"}, "reaching": {"audio": {"gb": ["w/gb/gb_reaching.mp3"]}, "gb": "|ˈriːtʃɪŋ|", "wforms": " ing-форма дієслова to reach", "awords": ["reach"], "trans": ""}, "reach": {"trans": "дійти, доходити, доїхати, доїжджати, досягати", "audio": {"gb": ["w/gb/gb_reach.mp3"]}, "gb": "|riːtʃ|"}, "safety": {"trans": "безпека, Безпека, Запобіжник", "audio": {"gb": ["w/gb/gb_safety.mp3"]}, "gb": "|ˈseɪfti|"}, "where": {"trans": "де, звідки, куди", "audio": {"gb": ["w/gb/gb_where.mp3"]}, "gb": "|weə|"}, "found": {"trans": "виправдовувати, розплавляти, розтоплювати, лити, виливати", "audio": {"gb": ["w/gb/gb_found.mp3"]}, "gb": "|faʊnd|", "wforms": " 2-а,3-я форма дієслова to find", "awords": ["find"]}, "find": {"trans": "знайти, знаходити, виявити", "audio": {"gb": ["w/gb/gb_find.mp3"]}, "gb": "|faɪnd|", "wforms": " irregular verb:  p.t. —  found  p.p. —  found "}, "once": {"trans": "раз, один раз, колись", "audio": {"gb": ["w/gb/gb_once.mp3"]}, "gb": "|wʌns|"}, "entered": {"audio": {"gb": ["w/gb/gb_entered.mp3"]}, "gb": "|ˈentəd|", "wforms": " 2-а,3-я форма дієслова to enter", "awords": ["enter"], "trans": ""}, "enter": {"trans": "входити, увійти, ввійти", "audio": {"gb": ["w/gb/gb_enter.mp3"]}, "gb": "|ˈentə|"}, "upon": {"trans": "на", "audio": {"gb": ["w/gb/gb_upon.mp3"]}, "gb": "|əˈpɒn|"}, "new": {"trans": "новий, нова, свіжий, new (C++)", "audio": {"gb": ["w/gb/gb_new.mp3"]}, "gb": "|njuː|"}, "duties": {"audio": {"gb": ["w/gb/gb_duties.mp3"]}, "gb": "|ˈdjuːtɪz|", "wforms": " множина для іменника duty", "awords": ["duty"], "trans": ""}, "duty": {"trans": "обов'язок, борг, Обов'язок, Мито, адвалерне мито", "audio": {"gb": ["w/gb/gb_duty.mp3"]}, "gb": "|ˈdjuːti|"}}