[{"play": 0}, ["How", "|haʊ|"], " ", ["God", "|ɡɒd|"], " ", ["makes", "|ˈmeɪks|"], " ", ["his", "|hɪz|"], " ", ["colours", "|ˈkʌləz|"], ", ", ["I"], " ", ["know", "|nəʊ|"], " ", ["not"], ", ", ["but", "|bʌt|"], " ", ["I'm"], " ", ["pursuing", "|pəˈsjuːɪŋ|"], " ", ["him", "|hɪm|"], " ", ["through", "|θruː|"], " ", ["his"], " ", ["chemicals", "|ˈkemɪkəlz|"], ". <br>", ["They", "|ðeɪ|"], " ", ["said", "|ˈsed|"], " ", ["you", "|ju|"], " ", ["were", "|wɜː|"], " ", ["a"], " ", ["doctor", "|ˈdɒktə|"], ".  <br>", ["A"], " ", ["sheep", "|ʃiːp|"], " ", ["is"], " ", ["a"], " ", ["sheep"], ", ", ["but"], " ", ["also", "|ˈɔːlsəʊ|"], " ", ["meat", "|miːt|"], " ", ["and", "|ænd|"], " ", ["wool", "|wʊl|"], ". ", ["This", "|ðɪs|"], " ", ["is"], " ", ["my", "|maɪ|"], " ", ["pastime", "|ˈpɑːstæɪm|"], "... ", ["fixing", "|ˈfɪksɪŋ|"], " ", ["colours"], " ", ["in", "|ɪn|"], " ", ["cloth", "|klɒθ|"], ". ", ["The", "|ði:|"], " ", ["demand", "|dɪˈmɑːnd|"], " ", ["for", "|fɔː|"], " ", ["flags", "|flæɡz|"], " ", ["is"], " ", ["always", "|ˈɔːlweɪz|"], " ", ["high", "|haɪ|"], " ", ["in"], " ", ["times", "|taɪmz|"], " ", ["of", "|ɒv|"], " ", ["war", "|wɔː|"], ".", {"compare": "di"}, "<br>", {"play": 26}, ["So", "|səʊ|"], " ", ["you"], " ", ["are", "|ɑː|"], " ", ["three", "|θriː|"], " ", ["things", "|ˈθɪŋz|"], ", ", ["yes", "|jes|"], "?  ", ["You", "|ju|"], " ", ["are"], " ", ["a"], " ", ["doctor"], "... ", ["you"], " ", ["are"], " ", ["a"], " ", ["merchant", "|ˈmɜːtʃ(ə)nt|"], "...  ", ["and"], " ", ["you"], " ", ["are"], " ", ["a"], " ", ["spy", "|spaɪ|"], ".  <br>", ["Unless", "|ʌnˈles|"], " ", ["you"], " ", ["tell", "|tel|"], " ", ["me", "|miː|"], " ", ["who", "|huː|"], " ", ["sent", "|sent|"], " ", ["you"], ", ", ["I"], " ", ["will", "|wɪl|"], " ", ["have", "|hæv|"], " ", ["to", "|tuː|"], " ", ["ask", "|ɑːsk|"], " ", ["you"], " ", ["to"], " ", ["leave", "|liːv|"], " ", ["at", "|æt|"], " ", ["the", "|ði:|"], " ", ["point", "|pɔɪnt|"], " ", ["of"], " ", ["a"], " ", ["gun", "|ɡʌn|"], ". <br>", ["A"], " ", ["man", "|mæn|"], " ", ["who"], " ", ["called", "|kɔːld|"], " ", ["himself", "|hɪmˈself|"], " ", ["Colonay"], ".  <br>", ["Uh"], "-", ["huh", "|hʌ|"], ". ", ["Not"], " ", ["yet", "|jet|"], " ", ["in"], " ", ["Hell", "|hel|"], "?  <br>", ["No", "|nəʊ|"], ", ", ["Ponta"], " ", ["Delgada"], " ", ["and"], " ", ["the"], " ", ["Azores", "|əˈzɔːz|"], ".  ", ["Similar", "|ˈsɪmɪlə|"], ".", {"compare": "di"}, "<br>", {"play": 54}, ["You"], " ", ["should", "|ʃʊd|"], " ", ["know"], " ", ["the"], " ", ["wound", "|wuːnd|"], " ", ["in"], " ", ["the"], " ", ["shoulder", "|ˈʃəʊldə|"], " - ", ["is"], " ", ["no", "|nəʊ|"], " ", ["longer", "|ˈlɒŋɡə|"], " ", ["used", "|ˈjuːzd|"], " ", ["by", "|baɪ|"], " ", ["us", "|ʌs|"], " ", ["as", "|æz|"], " ", ["a"], " ", ["signal", "|ˈsɪɡn(ə)l|"], ". - ", ["No"], "? <br>", ["No"], ", ", ["we", "|wi|"], " ", ["change", "|tʃeɪn(d)ʒ|"], " ", ["the"], " ", ["codes", "|kəʊdz|"], " ", ["when", "|wen|"], " ", ["we"], " ", ["think", "|θɪŋk|"], " ", ["that", "|ðæt|"], " ", ["perhaps", "|pəˈhæps|"], " <br>", ["the"], " ", ["scum", "|skʌm|"], " ", ["British", "|ˈbrɪtɪʃ|"], " ", ["have"], " ", ["overtaken", "|ˌəʊvəˈteɪkən|"], " ", ["it"], ".  <br>", ["And", "|ænd|"], " ", ["you"], " ", ["do", "|duː|"], " ", ["not"], " ", ["trust", "|trʌst|"], " ", ["the"], " ", ["name", "|neɪm|"], " ", ["Colonay"], "? <br>", ["What", "|wɒt|"], " ", ["do"], " ", ["you"], " ", ["want", "|wɒnt|"], "?  <br>", ["I"], " ", ["want"], " ", ["a"], " ", ["line", "|laɪn|"], " ", ["of"], " ", ["conference", "|ˈkɒnf(ə)r(ə)ns|"], "  ", ["with", "|wɪð|"], " ", ["the"], " ", ["President", "|ˈprezɪdənt|"], " ", ["of"], " ", ["the"], " 15 ", ["states", "|steɪts|"], " ", ["of"], " ", ["America", "|əˈmerɪkə|"], ". ", ["My", "|maɪ|"], " ", ["name"], " ", ["is"], " ", ["James", "|dʒeɪmz|"], " ", ["Delaney"], ".", {"compare": "di"}, "<br>", {"play": 79}, ["That", "|ðæt|"], " ", ["name"], " ", ["means", "|miːnz|"], " ", ["nothing", "|ˈnʌθɪŋ|"], ".  <br>", ["But", "|bʌt|"], " ", ["it"], " ", ["will"], " ", ["to"], " ", ["the"], " ", ["President"], " ", ["and"], " ", ["his"], " ", ["representatives", "|ˌreprɪˈzentətɪvz|"], ", ", ["who"], " ", ["are"], " ", ["travelling", "|ˈtrævəlɪŋ|"], " ", ["to"], " ", ["the"], " ", ["negotiations", "|nɪˌɡəʊʃɪˈeɪʃənz|"], " ", ["in"], " ", ["Ghent", "|ɡent|"], ". ", ["The"], " ", ["border", "|ˈbɔːdə|"], " ", ["between", "|bɪˈtwiːn|"], " ", ["the"], " ", ["United", "|juˈnaɪtɪd|"], " ", ["States", "|steɪts|"], " ", ["and"], " ", ["Canada", "|ˈkanədə|"], " ", ["is"], " ", ["being", "|ˈbiːɪŋ|"], " ", ["drawn", "|drɔːn|"], " ", ["up", "|ʌp|"], " ", ["in"], " ", ["a"], " ", ["very", "|ˈveri|"], "... ", ["quiet", "|ˈkwaɪət|"], "... ", ["closed", "|kləʊzd|"], " ", ["room", "|ruːm|"], ", ", ["no"], "? ", ["You"], " ", ["see", "|siː|"], ", ", ["I"], " ", ["have"], " ", ["something", "|ˈsʌmθɪŋ|"], " ", ["of"], " ", ["great", "|ɡreɪt|"], " ", ["value", "|ˈvæljuː|"], " ", ["to"], " ", ["your", "|jə|"], " ", ["nation", "|ˈneɪʃ(ə)n|"], ". ", ["Something", "|ˈsʌmθɪŋ|"], " ", ["the"], " ", ["British"], " ", ["are"], " ", ["trying", "|ˈtraɪɪŋ|"], " ", ["to"], " ", ["kill", "|kɪl|"], " ", ["me"], " ", ["for"], ".", {"compare": "di"}, "<br>", {"play": 104}, ["And"], " ", ["what", "|wɒt|"], "? ", ["You"], " ", ["seek", "|siːk|"], " ", ["protection", "|prəˈtekʃ(ə)n|"], "?  <br>", ["I"], " ", ["have"], " ", ["demands", "|dɪˈmɑːndz|"], ".  <br>", ["Demands", "|dɪˈmɑːndz|"], "?  <br>", ["You"], " ", ["tell"], " ", ["Carlsbad"], " ", ["my"], " ", ["name"], ".  <br>- ", ["And"], " ", ["who's"], " ", ["Carlsbad"], "? - ", ["Carlsbad"], " ", ["is"], " ", ["the"], " ", ["head", "|hed|"], " <br>", ["of"], " ", ["the"], " ", ["American", "|əˈmerɪk(ə)n|"], " ", ["Society", "|səˈsaɪɪti|"], " ", ["of"], " ", ["Secret", "|ˈsiːkrɪt|"], " ", ["Correspondence", "|kɒrɪˈspɒnd(ə)ns|"], " ", ["in"], " ", ["London", "|ˈlʌndən|"], ". ", ["I"], " ", ["know"], " ", ["that"], " ", ["name"], ", ", ["because", "|bɪˈkəz|"], " ", ["Colonay"], " ", ["told", "|təʊld|"], " ", ["me"], " ", ["it"], ". ", ["He", "|hi|"], " ", ["was", "|wɒz|"], " ", ["drunk", "|drʌŋk|"], ". ", ["He"], " ", ["was"], " ", ["trying"], " ", ["to"], " ", ["push", "|pʊʃ|"], " ", ["his"], " ", ["jelly", "|ˈdʒeli|"], " ", ["up"], " ", ["a"], " ", ["whore", "|hɔː|"], ". <br>", ["Carlsbad"], " ", ["will"], " ", ["know"], " ", ["my"], " ", ["name"], " ", ["and"], " ", ["know"], " ", ["my"], " ", ["business", "|ˈbɪznəs|"], ".", {"compare": "di"}, "<br>", {"play": 143}, ["I'm"], " ", ["afraid", "|əˈfreɪd|"], " ", ["you've"], " ", ["used"], " ", ["the"], " ", ["wrong", "|rɒŋ|"], " ", ["words", "|ˈwɜːdz|"], ". ", ["Get", "|ɡet|"], " ", ["out", "|aʊt|"], ".  <br>", ["Do", "|duː|"], " ", ["you"], " ", ["treat", "|triːt|"], " ", ["sickness", "|ˈsɪknəs|"], " ", ["of"], " ", ["the"], " ", ["mind", "|maɪnd|"], ", ", ["Doctor", "|ˈdɒktə|"], "? <br>", ["Just", "|dʒəst|"], " ", ["keep", "|kiːp|"], " ", ["walking", "|ˈwɔːkɪŋ|"], ".  ", ["You're"], " ", ["mad", "|mæd|"], " ", ["to"], " ", ["have"], " ", ["even", "|ˈiːvn|"], " ", ["come", "|kʌm|"], " ", ["here", "|hɪə|"], ".  ", ["We", "|wi|"], " ", ["are"], " ", ["an"], " ", ["angry", "|ˈæŋɡri|"], " ", ["nation"], ".  <br>", ["Yeah", "|jeə|"], ".  ", ["I'm"], " ", ["counting", "|ˈkaʊntɪŋ|"], " ", ["on", "|ɒn|"], " ", ["it"], ".  ", ["Good", "|ɡʊd|"], " ", ["day", "|deɪ|"], ".", {"compare": "di"}]