{"tell": {"trans": "казати, наказувати, запевняти, Тель", "audio": {"gb": ["w/gb/gb_tell.mp3"]}, "gb": "|tel|", "wforms": " irregular verb:  p.t. —  told  p.p. —  told "}, "her": {"trans": "її, свій, вона, вимова", "audio": {"gb": ["w/gb/gb_her.mp3"]}, "gb": "|hə|"}, "how": {"trans": "як, скільки", "audio": {"gb": ["w/gb/gb_how.mp3"]}, "gb": "|haʊ|"}, "started": {"audio": {"gb": ["w/gb/gb_started.mp3"]}, "gb": "|ˈstɑːtɪd|", "wforms": " 2-а,3-я форма дієслова to start", "awords": ["start"], "trans": ""}, "start": {"trans": "починати, початок, починатися", "audio": {"gb": ["w/gb/gb_start.mp3"]}, "gb": "|stɑːt|"}, "lying": {"trans": "", "audio": {"gb": ["w/gb/gb_lying.mp3"]}, "gb": "|ˈlaɪɪŋ|", "wforms": " ing-форма дієслова to lie", "awords": ["lie"]}, "lie": {"trans": "лежати, брехати, брехня", "audio": {"gb": ["w/gb/gb_lie.mp3"]}, "gb": "|laɪ|", "wforms": " irregular verb:  p.t. —  lay  p.p. —  lain "}, "awake": {"trans": "просипатися, прокидатися, пильний", "audio": {"gb": ["w/gb/gb_awake.mp3"]}, "gb": "|əˈweɪk|", "wforms": " irregular verb:  p.t. —  awoke  p.p. —  awoken "}, "wishing": {"audio": {"gb": ["w/gb/gb_wishing.mp3"]}, "gb": "|ˈwɪʃɪŋ|", "wforms": " ing-форма дієслова to wish", "awords": ["wish"], "trans": ""}, "wish": {"trans": "бажати, побажати, бажання", "audio": {"gb": ["w/gb/gb_wish.mp3"]}, "gb": "|wɪʃ|"}, "Glen": {"trans": "Глен", "audio": {"gb": ["w/gb/gb_glen.mp3"]}, "gb": "|ɡlen|"}, "was": {"trans": "читач", "audio": {"gb": ["w/gb/gb_was.mp3"]}, "gb": "|wɒz|"}, "dead": {"trans": "мертвий, смерть, точно", "audio": {"gb": ["w/gb/gb_dead.mp3"]}, "gb": "|ded|"}, "Well": {"trans": "добре, колодязь, гарно", "audio": {"gb": ["w/gb/gb_well.mp3"]}, "gb": "|wel|"}, "exactly": {"trans": "точно, якраз, саме", "audio": {"gb": ["w/gb/gb_exactly.mp3"]}, "gb": "|ɪɡˈzæk(t)li|"}, "want": {"trans": "хотіти, бажати, бажання", "audio": {"gb": ["w/gb/gb_want.mp3"]}, "gb": "|wɒnt|"}, "him": {"trans": "його, йому, він", "audio": {"gb": ["w/gb/gb_him.mp3"]}, "gb": "|hɪm|"}, "to": {"trans": "до, щоб, на, аби", "audio": {"gb": ["w/gb/gb_to.mp3"]}, "gb": "|tuː|"}, "be": {"trans": "бути, знаходитися, існувати, з'являтися, являтися", "audio": {"gb": ["w/gb/gb_be.mp3"]}, "gb": "|bi|", "wforms": " irregular verb:  p.t. —  were/was  p.p. —  been "}, "in": {"trans": "в, у, ув, уві, у травні", "audio": {"gb": ["w/gb/gb_in.mp3"]}, "gb": "|ɪn|"}, "any": {"trans": "скільки-небудь, якийсь, абиякий", "audio": {"gb": ["w/gb/gb_any.mp3"]}, "gb": "|ˈeni|"}, "pain": {"trans": "біль, боліти, мука, ломота", "audio": {"gb": ["w/gb/gb_pain.mp3"]}, "gb": "|peɪn|"}, "or": {"trans": "або, чи, Золото", "audio": {"gb": ["w/gb/gb_or.mp3"]}, "gb": "|ɔː|"}, "suffer": {"trans": "страждати, хворіти, перетерпіти", "audio": {"gb": ["w/gb/gb_suffer.mp3"]}, "gb": "|ˈsʌfə|"}, "anything": {"trans": "що-небудь, ніщо, абищо", "audio": {"gb": ["w/gb/gb_anything.mp3"]}, "gb": "|ˈeniθɪŋ|"}, "just": {"trans": "просто, тільки, щойно, справедливий", "audio": {"gb": ["w/gb/gb_just.mp3"]}, "gb": "|dʒəst|"}, "wanted": {"trans": "", "audio": {"gb": ["w/gb/gb_wanted.mp3"]}, "gb": "|ˈwɒntɪd|", "wforms": " 2-а,3-я форма дієслова to want", "awords": ["want"]}, "there": {"trans": "там, туди, ось, от", "audio": {"gb": ["w/gb/gb_there.mp3"]}, "gb": "|ðeə|"}, "more": {"trans": "більш, More, Більше", "audio": {"gb": ["w/gb/gb_more.mp3"]}, "gb": "|mɔː|"}, "would": {"trans": "", "audio": {"gb": ["w/gb/gb_would.mp3"]}, "gb": "|wʊd|"}, "fantasize": {"trans": "", "audio": {"gb": ["w/gb/gb_fantasize.mp3"]}, "gb": "|ˈfæntəsæɪz|"}, "about": {"trans": "про, приблизно, близько", "audio": {"gb": ["w/gb/gb_about.mp3"]}, "gb": "|əˈbaʊt|"}, "the": {"trans": "the", "audio": {"gb": ["w/gb/gb_the.mp3"]}, "gb": "|ði:|"}, "moment": {"trans": "момент, мить, хвилина", "audio": {"gb": ["w/gb/gb_moment.mp3"]}, "gb": "|ˈməʊm(ə)nt|"}, "when": {"trans": "коли, якщо", "audio": {"gb": ["w/gb/gb_when.mp3"]}, "gb": "|wen|"}, "I’d": {"trans": "скорочено від I had, I should/ I would", "audio": {"gb": ["w/gb/gb_i.mp3"]}, "gb": "|aɪd|"}, "get": {"trans": "отримувати, дістати, діставати", "audio": {"gb": ["w/gb/gb_get.mp3"]}, "gb": "|ɡet|", "wforms": " irregular verb:  p.t. —  got  p.p. —  got "}, "call": {"trans": "звати, кликати, подзвонити", "audio": {"gb": ["w/gb/gb_call.mp3"]}, "gb": "|kɔːl|"}, "from": {"trans": "від, з", "audio": {"gb": ["w/gb/gb_from.mp3"]}, "gb": "|frɒm|"}, "police": {"trans": "поліція, міліція, поліцiя", "audio": {"gb": ["w/gb/gb_police.mp3"]}, "gb": "|pəˈliːs|"}, "officer": {"trans": "офіцер, чиновник, офіцерський", "audio": {"gb": ["w/gb/gb_officer.mp3"]}, "gb": "|ˈɒfɪsə|"}, "deep": {"trans": "глибокий", "audio": {"gb": ["w/gb/gb_deep.mp3"]}, "gb": "|diːp|"}, "voice": {"trans": "голос, Дзвінкість, застава, стан", "audio": {"gb": ["w/gb/gb_voice.mp3"]}, "gb": "|vɔɪs|"}, "say": {"trans": "казати, говорити, сказати, повідати, вимовити", "audio": {"gb": ["w/gb/gb_say.mp3"]}, "gb": "|seɪ|", "wforms": " irregular verb:  p.t. —  said  p.p. —  said "}, "so": {"trans": "так, такий, тож", "audio": {"gb": ["w/gb/gb_so.mp3"]}, "gb": "|səʊ|"}, "sorry": {"trans": "пробачте, перепрошую, пробач", "audio": {"gb": ["w/gb/gb_sorry.mp3"]}, "gb": "|ˈsɒri|"}, "but": {"trans": "але, а, крім, однак, окрім", "audio": {"gb": ["w/gb/gb_but.mp3"]}, "gb": "|bʌt|"}, "got": {"trans": "", "audio": {"gb": ["w/gb/gb_got.mp3"]}, "gb": "|ˈɡɒt|", "wforms": " 2-а,3-я форма дієслова to get", "awords": ["get"]}, "bad": {"trans": "злий, поганий, кепський", "audio": {"gb": ["w/gb/gb_bad.mp3"]}, "gb": "|bæd|"}, "news": {"trans": "новини, вісті, вість, інформаційний", "audio": {"gb": ["w/gb/gb_news.mp3"]}, "gb": "|njuːz|"}, "The": {"trans": "транскрипція", "audio": {"gb": ["w/gb/gb_the.mp3"]}, "gb": "|ði:|"}, "anticipation": {"trans": "сподівання, передчуття, передбачення", "audio": {"gb": ["w/gb/gb_anticipation.mp3"]}, "gb": "|æntɪsɪˈpeɪʃ(ə)n|"}, "of": {"trans": "про", "audio": {"gb": ["w/gb/gb_of.mp3"]}, "gb": "|ɒv|"}, "next": {"trans": "наступний, майбутній, черговий", "audio": {"gb": ["w/gb/gb_next.mp3"]}, "gb": "|nekst|"}, "bit": {"trans": "біт, шматочок, шматок", "audio": {"gb": ["w/gb/gb_bit.mp3"]}, "gb": "|bɪt|", "wforms": " 2-а форма неправильного дієслова to bite", "awords": ["bite"]}, "bite": {"trans": "кусати, укусити, гризтити", "audio": {"gb": ["w/gb/gb_bite.mp3"]}, "gb": "|baɪt|", "wforms": " irregular verb:  p.t. —  bit  p.p. —  bitten "}, "almost": {"trans": "сливе, майже, почти, наче, мало не", "audio": {"gb": ["w/gb/gb_almost.mp3"]}, "gb": "|ˈɔːlməʊst|"}, "used": {"trans": "", "audio": {"gb": ["w/gb/gb_used.mp3"]}, "gb": "|ˈjuːzd|", "wforms": " 2-а,3-я форма дієслова to use", "awords": ["use"]}, "use": {"trans": "використовувати, використати, вживання", "audio": {"gb": ["w/gb/gb_use.mp3"]}, "gb": "|juːz|"}, "make": {"trans": "робити, зробити, виготовляти", "audio": {"gb": ["w/gb/gb_make.mp3"]}, "gb": "|meɪk|", "wforms": " irregular verb:  p.t. —  made  p.p. —  made "}, "me": {"trans": "мене, мені, ме, мої дії", "audio": {"gb": ["w/gb/gb_me.mp3"]}, "gb": "|miː|"}, "giggle": {"trans": "", "audio": {"gb": ["w/gb/gb_giggle.mp3"]}, "gb": "|ˈɡɪɡ(ə)l|"}, "afraid": {"trans": "наляканий, зляканий", "audio": {"gb": ["w/gb/gb_afraid.mp3"]}, "gb": "|əˈfreɪd|"}, "your": {"trans": "ваш, твій", "audio": {"gb": ["w/gb/gb_your.mp3"]}, "gb": "|jə|"}, "husband": {"trans": "чоловік, муж, Чоловік", "audio": {"gb": ["w/gb/gb_husband.mp3"]}, "gb": "|ˈhʌzbənd|"}, "has": {"trans": "є", "audio": {"gb": ["w/gb/gb_has.mp3"]}, "gb": "|hæz|", "wforms": " present tense(he/she/it) для дієслова to have", "awords": ["have"]}, "have": {"trans": "мати, у, в, повинен", "audio": {"gb": ["w/gb/gb_have.mp3"]}, "gb": "|hæv|", "wforms": " irregular verb:  p.t. —  had  p.p. —  had "}, "been": {"trans": "", "audio": {"gb": ["w/gb/gb_been.mp3"]}, "gb": "|biːn|", "wforms": " 3-я форма неправильного дієслова to be", "awords": ["be"]}, "killed": {"trans": "", "audio": {"gb": ["w/gb/gb_killed.mp3"]}, "gb": "|kɪld|", "wforms": " 2-а,3-я форма дієслова to kill", "awords": ["kill"]}, "kill": {"trans": "вбивати, убивати, вбити", "audio": {"gb": ["w/gb/gb_kill.mp3"]}, "gb": "|kɪl|"}, "accident": {"trans": "аварія, випадок, катастрофа", "audio": {"gb": ["w/gb/gb_accident.mp3"]}, "gb": "|ˈæksɪd(ə)nt|"}, "then": {"trans": "тоді, потім", "audio": {"gb": ["w/gb/gb_then.mp3"]}, "gb": "|ðen|"}, "saw": {"trans": "пила, пилка, Пилка", "audio": {"gb": ["w/gb/gb_saw.mp3"]}, "gb": "|ˈsɔː|", "wforms": " irregular verb:  p.t. —  sawed  p.p. —  sawn "}, "myself": {"trans": "себе, ся, собою", "audio": {"gb": ["w/gb/gb_myself.mp3"]}, "gb": "|maɪˈself|"}, "really": {"trans": "дійсно, справді, правдивий", "audio": {"gb": ["w/gb/gb_really.mp3"]}, "gb": "|ˈriːəli|"}, "sobbing": {"trans": "", "audio": {"gb": ["w/gb/gb_sobbing.mp3"]}, "gb": "|ˈsɒbɪŋ|", "wforms": " ing-форма дієслова to sob", "awords": ["sob"]}, "sob": {"trans": "схлипувати", "audio": {"gb": ["w/gb/gb_sob.mp3"]}, "gb": "|sɒb|"}, "and": {"trans": "і, й, та", "audio": {"gb": ["w/gb/gb_and.mp3"]}, "gb": "|ænd|"}, "picking": {"trans": "добір, селекція", "audio": {"gb": ["w/gb/gb_picking.mp3"]}, "gb": "|ˈpɪkɪŋ|", "wforms": " ing-форма дієслова to pick", "awords": ["pick"]}, "pick": {"trans": "збирати, вибирати, обирати", "audio": {"gb": ["w/gb/gb_pick.mp3"]}, "gb": "|pɪk|"}, "up": {"trans": "догори, вгору, вгорі", "audio": {"gb": ["w/gb/gb_up.mp3"]}, "gb": "|ʌp|"}, "phone": {"trans": "телефон, подзвонити, дзвонити, мобільний телефон, телефонувати", "audio": {"gb": ["w/gb/gb_phone.mp3"]}, "gb": "|fəʊn|"}, "ring": {"trans": "кільце, перстень, дзвонити", "audio": {"gb": ["w/gb/gb_ring.mp3"]}, "gb": "|rɪŋ|", "wforms": " irregular verb:  p.t. —  rang  p.p. —  rung "}, "his": {"trans": "його, свій", "audio": {"gb": ["w/gb/gb_his.mp3"]}, "gb": "|hɪz|"}, "mum": {"trans": "мама, неня, мати", "audio": {"gb": ["w/gb/gb_mum.mp3"]}, "gb": "|mʌm|"}, "Mary": {"trans": "Марія, Богородиця, Мері", "audio": {"gb": ["w/gb/gb_mary.mp3"]}, "gb": "|ˈmeəri|"}, "some": {"trans": "трохи, кілька, деякий", "audio": {"gb": ["w/gb/gb_some.mp3"]}, "gb": "|sʌm|"}, "can": {"trans": "могти, вміти, уміти", "audio": {"gb": ["w/gb/gb_can.mp3"]}, "gb": "|kæn|"}, "hear": {"trans": "чути, почувати, почути, учувати", "audio": {"gb": ["w/gb/gb_hear.mp3"]}, "gb": "|hɪə|", "wforms": " irregular verb:  p.t. —  heard  p.p. —  heard "}, "shock": {"trans": "шок, шокувати", "audio": {"gb": ["w/gb/gb_shock.mp3"]}, "gb": "|ʃɒk|"}, "gasp": {"trans": "задихатися", "audio": {"gb": ["w/gb/gb_gasp.mp3"]}, "gb": "|ɡɑːsp|"}, "feel": {"trans": "відчувати, відчути, почувати", "audio": {"gb": ["w/gb/gb_feel.mp3"]}, "gb": "|fiːl|", "wforms": " irregular verb:  p.t. —  felt  p.p. —  felt "}, "grief": {"trans": "горе, жаль, Горе, горі", "audio": {"gb": ["w/gb/gb_grief.mp3"]}, "gb": "|ɡriːf|"}, "sympathy": {"trans": "співчуття, Симпатія", "audio": {"gb": ["w/gb/gb_sympathy.mp3"]}, "gb": "|ˈsɪmpəθi|"}, "friends": {"audio": {"gb": ["w/gb/gb_friends.mp3"]}, "gb": "|frendz|", "wforms": " present tense(he/she/it) для дієслова to friend, множина для іменника friend", "awords": ["friend"], "trans": "друзі"}, "friend": {"trans": "друг, приятель, подруга", "audio": {"gb": ["w/gb/gb_friend.mp3"]}, "gb": "|frend|"}, "at": {"trans": "біля, в, у", "audio": {"gb": ["w/gb/gb_at.mp3"]}, "gb": "|æt|"}, "my": {"trans": "мій", "audio": {"gb": ["w/gb/gb_my.mp3"]}, "gb": "|maɪ|"}, "loss": {"trans": "втрата, шкода, зникнення, пропажа", "audio": {"gb": ["w/gb/gb_loss.mp3"]}, "gb": "|lɒs|"}, "gathering": {"trans": "збори, Збиральництво", "audio": {"gb": ["w/gb/gb_gathering.mp3"]}, "gb": "|ˈɡæð(ə)rɪŋ|", "wforms": " ing-форма дієслова to gather", "awords": ["gather"]}, "gather": {"trans": "збирати, зібрати, нагноїтися", "audio": {"gb": ["w/gb/gb_gather.mp3"]}, "gb": "|ˈɡæðə|"}, "family": {"trans": "родина, сім'я, сім’я", "audio": {"gb": ["w/gb/gb_family.mp3"]}, "gb": "|ˈfæməli|"}, "around": {"trans": "всюди, навколо, навкруги", "audio": {"gb": ["w/gb/gb_around.mp3"]}, "gb": "|əˈraʊnd|"}, "Then": {"trans": "тоді, потім", "audio": {"gb": ["w/gb/gb_then.mp3"]}, "gb": "|ðen|"}, "secret": {"trans": "секрет, таємниця, конфіденційний", "audio": {"gb": ["w/gb/gb_secret.mp3"]}, "gb": "|ˈsiːkrɪt|"}, "thrill": {"trans": "тремтіння", "audio": {"gb": ["w/gb/gb_thrill.mp3"]}, "gb": "|θrɪl|"}, "Me": {"trans": "мене, мені, ме, мої дії", "audio": {"gb": ["w/gb/gb_me.mp3"]}, "gb": "|miː|"}, "grieving": {"trans": "", "audio": {"gb": ["w/gb/gb_grieving.mp3"]}, "gb": "|ˈɡriːvɪŋ|", "wforms": " ing-форма дієслова to grieve", "awords": ["grieve"]}, "grieve": {"trans": "", "audio": {"gb": ["w/gb/gb_grieve.mp3"]}, "gb": "|ɡriːv|"}, "widow": {"trans": "вдова, Вдова, удова", "audio": {"gb": ["w/gb/gb_widow.mp3"]}, "gb": "|ˈwɪdəʊ|"}, "Don’t": {"trans": "не", "audio": {"gb": ["w/gb/gb_don.mp3"]}, "gb": "|dəʊnt|"}, "laugh": {"trans": "сміятися, сміх", "audio": {"gb": ["w/gb/gb_laugh.mp3"]}, "gb": "|lɑːf|"}, "Of": {"trans": "про", "audio": {"gb": ["w/gb/gb_of.mp3"]}, "gb": "|ɒv|"}, "course": {"trans": "курс, хід, біг", "audio": {"gb": ["w/gb/gb_course.mp3"]}, "gb": "|kɔːs|"}, "actually": {"trans": "насправді, дійсно, фактично", "audio": {"gb": ["w/gb/gb_actually.mp3"]}, "gb": "|ˈæktʃuəli|"}, "happened": {"audio": {"gb": ["w/gb/gb_happened.mp3"]}, "gb": "|ˈhæpənd|", "wforms": " 2-а,3-я форма дієслова to happen", "awords": ["happen"], "trans": ""}, "happen": {"trans": "статися, траплятися, трапитися", "audio": {"gb": ["w/gb/gb_happen.mp3"]}, "gb": "|ˈhæp(ə)n|"}, "nearly": {"trans": "майже, сливе, приблизно", "audio": {"gb": ["w/gb/gb_nearly.mp3"]}, "gb": "|ˈnɪəli|"}, "as": {"trans": "як, коли, оскільки", "audio": {"gb": ["w/gb/gb_as.mp3"]}, "gb": "|æz|"}, "real": {"trans": "справжній, реальний, дійсний", "audio": {"gb": ["w/gb/gb_real.mp3"]}, "gb": "|rɪəl|"}, "For": {"trans": "для, бо, від", "audio": {"gb": ["w/gb/gb_for.mp3"]}, "gb": "|fɔː|"}, "sounded": {"audio": {"gb": ["w/gb/gb_sounded.mp3"]}, "gb": "|ˈsaʊndɪd|", "wforms": " 2-а,3-я форма дієслова to sound", "awords": ["sound"], "trans": ""}, "sound": {"trans": "звук, звучати, здоровий", "audio": {"gb": ["w/gb/gb_sound.mp3"]}, "gb": "|saʊnd|"}, "relieved": {"audio": {"gb": ["w/gb/gb_relieved.mp3"]}, "gb": "|rɪˈliːvd|", "wforms": " 2-а,3-я форма дієслова to relieve", "awords": ["relieve"], "trans": "облегшення, полегшення"}, "relieve": {"trans": "полегшувати", "audio": {"gb": ["w/gb/gb_relieve.mp3"]}, "gb": "|rɪˈliːv|"}, "that": {"trans": "що, той, те", "audio": {"gb": ["w/gb/gb_that.mp3"]}, "gb": "|ðæt|"}, "all": {"trans": "все, всі, кожен", "audio": {"gb": ["w/gb/gb_all.mp3"]}, "gb": "|ɔːl|"}, "over": {"trans": "по, понад", "audio": {"gb": ["w/gb/gb_over.mp3"]}, "gb": "|ˈəʊvə|"}, "she": {"trans": "вона, самиця", "audio": {"gb": ["w/gb/gb_she.mp3"]}, "gb": "|ʃi|"}, "put": {"trans": "класти, ставити, посадити", "audio": {"gb": ["w/gb/gb_put.mp3"]}, "gb": "|pʊt|", "wforms": " irregular verb:  p.t. —  put  p.p. —  put "}, "down": {"trans": "вниз, внизу, донизу", "audio": {"gb": ["w/gb/gb_down.mp3"]}, "gb": "|daʊn|"}, "weeping": {"trans": "", "audio": {"gb": ["w/gb/gb_weeping.mp3"]}, "gb": "|ˈwiːpɪŋ|", "wforms": " ing-форма дієслова to weep", "awords": ["weep"]}, "weep": {"trans": "плакати, відень, плакатилити сльози", "audio": {"gb": ["w/gb/gb_weep.mp3"]}, "gb": "|wiːp|", "wforms": " irregular verb:  p.t. —  wept  p.p. —  wept "}, "for": {"trans": "для, бо, від", "audio": {"gb": ["w/gb/gb_for.mp3"]}, "gb": "|fɔː|"}, "boy": {"trans": "хлопець, хлопчик, козачок, Хлопець, хлопець ''м''", "audio": {"gb": ["w/gb/gb_boy.mp3"]}, "gb": "|ˌbɔɪ|"}, "And": {"trans": "і, й, та", "audio": {"gb": ["w/gb/gb_and.mp3"]}, "gb": "|ænd|"}, "were": {"trans": "", "audio": {"gb": ["w/gb/gb_were.mp3"]}, "gb": "|wɜː|"}, "no": {"trans": "ні, не, жоден", "audio": {"gb": ["w/gb/gb_no.mp3"]}, "gb": "|nəʊ|"}, "handful": {"trans": "жменя", "audio": {"gb": ["w/gb/gb_handful.mp3"]}, "gb": "|ˈhæn(d)fʊl|"}, "Kate": {"trans": "Кейт, Катерина, Кет"}, "Waters": {"trans": "", "audio": {"gb": ["w/gb/gb_waters.mp3"]}, "gb": "|ˈwɔːtəz|", "wforms": " present tense(he/she/it) для дієслова to water, множина для іменника water", "awords": ["water"]}, "water": {"trans": "вода, водний, водяний", "audio": {"gb": ["w/gb/gb_water.mp3"]}, "gb": "|ˈwɔːtə|"}, "chirps": {"audio": {"gb": ["w/gb/gb_chirps.mp3"]}, "gb": "|tʃɜːps|", "wforms": " present tense(he/she/it) для дієслова to chirp", "awords": ["chirp"], "trans": ""}, "chirp": {"trans": "писк, верещати, пищання, цвірінчати, цвірінькати", "audio": {"gb": ["w/gb/gb_chirp.mp3"]}, "gb": "|tʃɜːp|"}, "needing": {"audio": {"gb": ["w/gb/gb_needing.mp3"]}, "gb": "|ˈniːdɪŋ|", "wforms": " ing-форма дієслова to need", "awords": ["need"], "trans": ""}, "need": {"trans": "потреба, необхідність, нужда", "audio": {"gb": ["w/gb/gb_need.mp3"]}, "gb": "|niːd|"}, "loo": {"trans": "вбиральня", "audio": {"gb": ["w/gb/gb_loo.mp3"]}, "gb": "|luː|"}, "making": {"trans": "", "audio": {"gb": ["w/gb/gb_making.mp3"]}, "gb": "|ˈmeɪkɪŋ|", "wforms": " ing-форма дієслова to make", "awords": ["make"]}, "another": {"trans": "інший, наступний, черговий", "audio": {"gb": ["w/gb/gb_another.mp3"]}, "gb": "|əˈnʌðə|"}, "cup": {"trans": "чашка, кубок, Чаша", "audio": {"gb": ["w/gb/gb_cup.mp3"]}, "gb": "|kʌp|"}, "tea": {"trans": "чай, чашка чаю, Підвечірок", "audio": {"gb": ["w/gb/gb_tea.mp3"]}, "gb": "|tiː|"}, "let": {"trans": "дозволити, дозволяти", "audio": {"gb": ["w/gb/gb_let.mp3"]}, "gb": "|let|", "wforms": " irregular verb:  p.t. —  let  p.p. —  let "}, "on": {"trans": "на, по", "audio": {"gb": ["w/gb/gb_on.mp3"]}, "gb": "|ɒn|"}, "with": {"trans": "з, зі, із", "audio": {"gb": ["w/gb/gb_with.mp3"]}, "gb": "|wɪð|"}, "giving": {"trans": "", "audio": {"gb": ["w/gb/gb_giving.mp3"]}, "gb": "|ˈɡɪvɪŋ|", "wforms": " ing-форма дієслова to give", "awords": ["give"]}, "give": {"trans": "давати, дати, дарувати", "audio": {"gb": ["w/gb/gb_give.mp3"]}, "gb": "|ɡɪv|", "wforms": " irregular verb:  p.t. —  gave  p.p. —  given "}, "mug": {"trans": "кухоль, гуртка, Кухоль", "audio": {"gb": ["w/gb/gb_mug.mp3"]}, "gb": "|mʌɡ|"}, "showing": {"trans": "показ", "audio": {"gb": ["w/gb/gb_showing.mp3"]}, "gb": "|ˈʃəʊɪŋ|", "wforms": " ing-форма дієслова to show", "awords": ["show"]}, "show": {"trans": "показувати, показати, вказувати", "audio": {"gb": ["w/gb/gb_show.mp3"]}, "gb": "|ʃəʊ|", "wforms": " irregular verb:  p.t. —  showed  p.p. —  shown "}, "downstairs": {"trans": "вниз, нижній", "audio": {"gb": ["w/gb/gb_downstairs.mp3"]}, "gb": "|ˌdaʊnˈsteəz|"}, "cloakroom": {"trans": "гардероб", "audio": {"gb": ["w/gb/gb_cloakroom.mp3"]}, "gb": "|ˈkləʊkruːm|"}, "When": {"trans": "коли, якщо", "audio": {"gb": ["w/gb/gb_when.mp3"]}, "gb": "|wen|"}, "gone": {"trans": "", "audio": {"gb": ["w/gb/gb_gone.mp3"]}, "gb": "|ɡɒn|", "wforms": " 3-я форма неправильного дієслова to go", "awords": ["go"]}, "go": {"trans": "іти, ходити, йти", "audio": {"gb": ["w/gb/gb_go.mp3"]}, "gb": "|ɡəʊ|", "wforms": " irregular verb:  p.t. —  went  p.p. —  gone "}, "look": {"trans": "дивитися, подивитися, виглядати", "audio": {"gb": ["w/gb/gb_look.mp3"]}, "gb": "|lʊk|"}, "room": {"trans": "кімната, покій, хата", "audio": {"gb": ["w/gb/gb_room.mp3"]}, "gb": "|ruːm|"}, "quickly": {"trans": "швидко", "audio": {"gb": ["w/gb/gb_quickly.mp3"]}, "gb": "|ˈkwɪkli|"}, "sure": {"trans": "впевнений, безпрограшний", "audio": {"gb": ["w/gb/gb_sure.mp3"]}, "gb": "|ʃʊə|"}, "nothing": {"trans": "ніщо, нічого, дрібниця, небуття", "audio": {"gb": ["w/gb/gb_nothing.mp3"]}, "gb": "|ˈnʌθɪŋ|"}, "out": {"trans": "аут, з", "audio": {"gb": ["w/gb/gb_out.mp3"]}, "gb": "|aʊt|"}, "No": {"trans": "ні, не, жоден", "audio": {"gb": ["w/gb/gb_no.mp3"]}, "gb": "|nəʊ|"}, "souvenirs": {"audio": {"gb": ["w/gb/gb_souvenirs.mp3"]}, "gb": "|ˌsuːvəˈnɪəz|", "wforms": " множина для іменника souvenir", "awords": ["souvenir"], "trans": ""}, "souvenir": {"trans": "сувенір", "audio": {"gb": ["w/gb/gb_souvenir.mp3"]}, "gb": "|ˌsuːvəˈnɪə|"}, "steal": {"trans": "красти, украсти, викрасти, Перехоплення, накрасти", "audio": {"gb": ["w/gb/gb_steal.mp3"]}, "gb": "|stiːl|", "wforms": " irregular verb:  p.t. —  stole  p.p. —  stolen "}, "warned": {"audio": {"gb": ["w/gb/gb_warned.mp3"]}, "gb": "|wɔːnd|", "wforms": " 2-а,3-я форма дієслова to warn", "awords": ["warn"], "trans": ""}, "warn": {"trans": "попередити, попереджати, остерігати", "audio": {"gb": ["w/gb/gb_warn.mp3"]}, "gb": "|wɔːn|"}, "He": {"trans": "він, воно", "audio": {"gb": ["w/gb/gb_he.mp3"]}, "gb": "|hi|"}, "told": {"trans": "", "audio": {"gb": ["w/gb/gb_told.mp3"]}, "gb": "|təʊld|", "wforms": " 2-а,3-я форма дієслова to tell", "awords": ["tell"]}, "stories": {"audio": {"gb": ["w/gb/gb_stories.mp3"]}, "gb": "|ˈstɔːrɪz|", "wforms": " множина для іменника story", "awords": ["story"], "trans": ""}, "story": {"trans": "оповідь, поверх, історія", "audio": {"gb": ["w/gb/gb_story.mp3"]}, "gb": "|ˈstɔːri|"}, "press": {"trans": "преса, пресувати, тиснути, натискати, давити", "audio": {"gb": ["w/gb/gb_press.mp3"]}, "gb": "|pres|"}, "toilet": {"trans": "туалет, унітаз, вбиральня, виходок, Туалет", "audio": {"gb": ["w/gb/gb_toilet.mp3"]}, "gb": "|ˈtɔɪlɪt|"}, "flush": {"trans": "рум'янець, краска, стадо", "audio": {"gb": ["w/gb/gb_flush.mp3"]}, "gb": "|flʌʃ|"}, "eventually": {"trans": "врешті-решт", "audio": {"gb": ["w/gb/gb_eventually.mp3"]}, "gb": "|ɪˈventʃuəli|"}, "reappears": {"audio": {"gb": ["w/gb/gb_reappears.mp3"]}, "gb": "|ˌriːəˈpɪəz|", "wforms": " present tense(he/she/it) для дієслова to reappear", "awords": ["reappear"], "trans": ""}, "reappear": {"trans": "", "audio": {"gb": ["w/gb/gb_reappear.mp3"]}, "gb": "|riːəˈpɪə|"}, "tray": {"trans": "піднос, Таця, таця", "audio": {"gb": ["w/gb/gb_tray.mp3"]}, "gb": "|treɪ|"}, "starts": {"audio": {"gb": ["w/gb/gb_starts.mp3"]}, "gb": "|stɑːts|", "wforms": " present tense(he/she/it) для дієслова to start, множина для іменника start", "awords": ["start"], "trans": ""}, "again": {"trans": "знову, знов, ще раз", "audio": {"gb": ["w/gb/gb_again.mp3"]}, "gb": "|əˈɡen|"}, "what": {"trans": "що, який", "audio": {"gb": ["w/gb/gb_what.mp3"]}, "gb": "|wɒt|"}, "remarkable": {"trans": "чудовий", "audio": {"gb": ["w/gb/gb_remarkable.mp3"]}, "gb": "|rɪˈmɑːkəb(ə)l|"}, "woman": {"trans": "жінка, жона, кобіта", "audio": {"gb": ["w/gb/gb_woman.mp3"]}, "gb": "|ˈwʊmən|"}, "must": {"trans": "мусити, повинен, повинний", "audio": {"gb": ["w/gb/gb_must.mp3"]}, "gb": "|mʌst|"}, "loyal": {"trans": "лояльний", "audio": {"gb": ["w/gb/gb_loyal.mp3"]}, "gb": "|ˈlɔɪəl|"}, "keep": {"trans": "тримати, донжон, продовжувати", "audio": {"gb": ["w/gb/gb_keep.mp3"]}, "gb": "|kiːp|", "wforms": " irregular verb:  p.t. —  kept  p.p. —  kept "}, "looking": {"trans": "", "audio": {"gb": ["w/gb/gb_looking.mp3"]}, "gb": "|ˈlʊkɪŋ|", "wforms": " ing-форма дієслова to look", "awords": ["look"]}, "wedding": {"trans": "весілля, Весілля, шлюб", "audio": {"gb": ["w/gb/gb_wedding.mp3"]}, "gb": "|ˈwedɪŋ|", "wforms": " ing-форма дієслова to wed", "awords": ["wed"]}, "wed": {"trans": "", "audio": {"gb": ["w/gb/gb_wed.mp3"]}, "gb": "|wed|", "wforms": " irregular verb:  p.t. —  wed or wedded  p.p. —  wed or wedded "}, "picture": {"trans": "картина, фотографія, ікона", "audio": {"gb": ["w/gb/gb_picture.mp3"]}, "gb": "|ˈpɪktʃə|"}, "wall": {"trans": "стіна, мур, Стіна", "audio": {"gb": ["w/gb/gb_wall.mp3"]}, "gb": "|wɔːl|"}, "above": {"trans": "над, вгорі, понад", "audio": {"gb": ["w/gb/gb_above.mp3"]}, "gb": "|əˈbʌv|"}, "gas": {"trans": "газ, бензин, газувати", "audio": {"gb": ["w/gb/gb_gas.mp3"]}, "gb": "|ɡæs|"}, "fire": {"trans": "вогонь, пожежа, піч", "audio": {"gb": ["w/gb/gb_fire.mp3"]}, "gb": "|ˈfaɪə|"}, "We": {"trans": "ми", "audio": {"gb": ["w/gb/gb_we.mp3"]}, "gb": "|wi|"}, "young": {"trans": "молодий, юний", "audio": {"gb": ["w/gb/gb_young.mp3"]}, "gb": "|jʌŋ|"}, "we": {"trans": "ми", "audio": {"gb": ["w/gb/gb_we.mp3"]}, "gb": "|wi|"}, "dressing": {"trans": "Перев'язка, поливка, підлива", "audio": {"gb": ["w/gb/gb_dressing.mp3"]}, "gb": "|ˈdresɪŋ|", "wforms": " ing-форма дієслова to dress", "awords": ["dress"]}, "dress": {"trans": "одяг, одягатися, сукня", "audio": {"gb": ["w/gb/gb_dress.mp3"]}, "gb": "|dres|"}, "our": {"trans": "наш", "audio": {"gb": ["w/gb/gb_our.mp3"]}, "gb": "|ˈaʊə|"}, "parents": {"trans": "батько, батьки", "audio": {"gb": ["w/gb/gb_parents.mp3"]}, "gb": "|ˈpeərənts|", "wforms": " множина для іменника parent", "awords": ["parent"]}, "parent": {"trans": "батько, родитель, батьки, батьківський", "audio": {"gb": ["w/gb/gb_parent.mp3"]}, "gb": "|ˈpeər(ə)nt|"}, "clothes": {"trans": "одежа, одяг, наряд", "audio": {"gb": ["w/gb/gb_clothes.mp3"]}, "gb": "|kləʊ(ð)z|", "wforms": " present tense(he/she/it) для дієслова to clothe", "awords": ["clothe"]}, "clothe": {"trans": "", "audio": {"gb": ["w/gb/gb_clothe.mp3"]}, "gb": "|kləʊð|", "wforms": " irregular verb:  p.t. —  clothed  p.p. —  clothed "}, "sees": {"audio": {"gb": ["w/gb/gb_sees.mp3"]}, "gb": "|ˈsiːz|", "wforms": " present tense(he/she/it) для дієслова to see, множина для іменника see", "awords": ["see"], "trans": ""}, "see": {"trans": "бачити, розуміти, видіти", "audio": {"gb": ["w/gb/gb_see.mp3"]}, "gb": "|siː|", "wforms": " irregular verb:  p.t. —  saw  p.p. —  seen "}, "takes": {"audio": {"gb": ["w/gb/gb_takes.mp3"]}, "gb": "|teɪks|", "wforms": " present tense(he/she/it) для дієслова to take, множина для іменника take", "awords": ["take"], "trans": ""}, "take": {"trans": "брати, взяти, узяти", "audio": {"gb": ["w/gb/gb_take.mp3"]}, "gb": "|teɪk|", "wforms": " irregular verb:  p.t. —  took  p.p. —  taken "}, "photo": {"trans": "фотографія, фото, знімок, фотка, фотознімок", "audio": {"gb": ["w/gb/gb_photo.mp3"]}, "gb": "|ˈfəʊtəʊ|"}, "off": {"trans": "", "audio": {"gb": ["w/gb/gb_off.mp3"]}, "gb": "|ɒf|"}, "She": {"trans": "вона, самиця", "audio": {"gb": ["w/gb/gb_she.mp3"]}, "gb": "|ʃi|"}, "perches": {"audio": {"gb": ["w/gb/gb_perches.mp3"]}, "gb": "|ˈpɜːtʃɪz|", "wforms": " present tense(he/she/it) для дієслова to perch, множина для іменника perch", "awords": ["perch"], "trans": ""}, "perch": {"trans": "окунь, Окунь, Перч (одиниця виміру), сідало подра", "audio": {"gb": ["w/gb/gb_perch.mp3"]}, "gb": "|pɜːtʃ|"}, "arm": {"trans": "рука, зброя, рукав", "audio": {"gb": ["w/gb/gb_arm.mp3"]}, "gb": "|ɑːm|"}, "chair": {"trans": "стілець, крісло, кафедра", "audio": {"gb": ["w/gb/gb_chair.mp3"]}, "gb": "|tʃeə|"}, "together": {"trans": "разом, спільно, докупи, воєдино", "audio": {"gb": ["w/gb/gb_together.mp3"]}, "gb": "|təˈɡeðə|"}, "September": {"trans": "вересень, Вересень, вересневий, зересень", "audio": {"gb": ["w/gb/gb_september.mp3"]}, "gb": "|sepˈtembə|"}, "sixth": {"trans": "шостий, секста", "audio": {"gb": ["w/gb/gb_sixth.mp3"]}, "gb": "|sɪksθ|"}, "day": {"trans": "день, доба, кожен, кожний", "audio": {"gb": ["w/gb/gb_day.mp3"]}, "gb": "|deɪ|"}, "tied": {"trans": "", "audio": {"gb": ["w/gb/gb_tied.mp3"]}, "gb": "|taɪd|", "wforms": " 2-а,3-я форма дієслова to tie", "awords": ["tie"]}, "tie": {"trans": "краватка, зaвʼязати, звʼязати", "audio": {"gb": ["w/gb/gb_tie.mp3"]}, "gb": "|taɪ|"}, "knot": {"trans": "вузол, Вузол, стадо", "audio": {"gb": ["w/gb/gb_knot.mp3"]}, "gb": "|nɒt|"}, "don’t": {"trans": "не", "audio": {"gb": ["w/gb/gb_don.mp3"]}, "gb": "|dəʊnt|"}, "know": {"trans": "знати, відати, впізнавати, вiдaти", "audio": {"gb": ["w/gb/gb_know.mp3"]}, "gb": "|nəʊ|", "wforms": " irregular verb:  p.t. —  knew  p.p. —  known "}, "why": {"trans": "чому, навіщо", "audio": {"gb": ["w/gb/gb_why.mp3"]}, "gb": "|waɪ|"}, "cry": {"trans": "плакати, кричати, вигук", "audio": {"gb": ["w/gb/gb_cry.mp3"]}, "gb": "|kraɪ|"}, "first": {"trans": "перший, спочатку, сперш, по-перше", "audio": {"gb": ["w/gb/gb_first.mp3"]}, "gb": "|fɜːst|"}, "tears": {"audio": {"gb": ["w/gb/gb_tears.mp3"]}, "gb": "|ˈtɪəz|", "wforms": " present tense(he/she/it) для дієслова to tear, множина для іменника tear", "awords": ["tear"], "trans": "сльози"}, "tear": {"trans": "сльоза, сльози, рвати, розрив, Сльози", "audio": {"gb": ["w/gb/gb_tear.mp3"]}, "gb": "|tɪə|", "wforms": " irregular verb:  p.t. —  tore  p.p. —  torn "}, "since": {"trans": "від, бо, з", "audio": {"gb": ["w/gb/gb_since.mp3"]}, "gb": "|sɪns|"}, "died": {"trans": "", "audio": {"gb": ["w/gb/gb_died.mp3"]}, "gb": "|daɪd|", "wforms": " 2-а,3-я форма дієслова to die", "awords": ["die"]}, "die": {"trans": "кістка, умирати, померти", "audio": {"gb": ["w/gb/gb_die.mp3"]}, "gb": "|daɪ|"}, "puts": {"audio": {"gb": ["w/gb/gb_puts.mp3"]}, "gb": "|ˈpʊts|", "wforms": " present tense(he/she/it) для дієслова to put", "awords": ["put"], "trans": ""}, "round": {"trans": "круглий, коло, круг, навколо, раунд", "audio": {"gb": ["w/gb/gb_round.mp3"]}, "gb": "|raʊnd|"}}